csdb/__init__.py
csdb/__main__.py
csdb/api_base.py
csdb/console.py
csdb/get_token.py
csdb/product.py
csdb/productType.py
csdb/session.py
csdb-1.1.0.dist-info/entry_points.txt
csdb-1.1.0.dist-info/WHEEL
csdb-1.1.0.dist-info/METADATA
csdb-1.1.0.dist-info/RECORD
