Metadata-Version: 2.1
Name: csdb
Version: 1.1.0
Summary: csdb python sdk for ep csdb
Author: zhangzhen
Author-email: zhangzhen@nao.cas.cn
Requires-Python: >=3.7
Classifier: Programming Language :: Python :: 3
Classifier: Programming Language :: Python :: 3.10
Classifier: Programming Language :: Python :: 3.7
Classifier: Programming Language :: Python :: 3.8
Classifier: Programming Language :: Python :: 3.9
Requires-Dist: click
Requires-Dist: click-completion
Requires-Dist: python-dateutil
Requires-Dist: requests
